[
 {
	"Name": "00000001",
	"StartDate": "2023-05-04",
	"EndDate": "2026-05-04",
	"Reason": "Issued as part of seed data insertion",
	"Status": "Active",
	"LoyaltyProgramMemberId": "0lMB0000000TW3uMAG",
	"LoyaltyProgramBadgeId": "0w8B0000000KyjkIAC"
},
 {
	"Name": "00000002",
	"StartDate": "2023-05-04",
	"EndDate": "2024-03-30",
	"Reason": "Issued as part of seed data insertion",
	"Status": "Active",
	"LoyaltyProgramMemberId": "0lMB0000000TW3uMAG",
	"LoyaltyProgramBadgeId": "0w8B0000000KyjlIAC"
}
 ]
 

